odoo/addons/product_pricelist_direct_print/README.rst
odoo/addons/product_pricelist_direct_print/__init__.py
odoo/addons/product_pricelist_direct_print/__manifest__.py
odoo/addons/product_pricelist_direct_print/data/mail_template_data.xml
odoo/addons/product_pricelist_direct_print/i18n/es.po
odoo/addons/product_pricelist_direct_print/i18n/fr.po
odoo/addons/product_pricelist_direct_print/i18n/it.po
odoo/addons/product_pricelist_direct_print/i18n/nl.po
odoo/addons/product_pricelist_direct_print/i18n/nl_NL.po
odoo/addons/product_pricelist_direct_print/i18n/product_pricelist_direct_print.pot
odoo/addons/product_pricelist_direct_print/i18n/tr.po
odoo/addons/product_pricelist_direct_print/readme/CONFIGURE.md
odoo/addons/product_pricelist_direct_print/readme/CONTRIBUTORS.md
odoo/addons/product_pricelist_direct_print/readme/DESCRIPTION.md
odoo/addons/product_pricelist_direct_print/readme/USAGE.md
odoo/addons/product_pricelist_direct_print/reports/report_product_pricelist.xml
odoo/addons/product_pricelist_direct_print/security/ir.model.access.csv
odoo/addons/product_pricelist_direct_print/static/description/icon.png
odoo/addons/product_pricelist_direct_print/static/description/index.html
odoo/addons/product_pricelist_direct_print/static/description/wizard_form.png
odoo/addons/product_pricelist_direct_print/tests/__init__.py
odoo/addons/product_pricelist_direct_print/tests/test_product_pricelist_direct_print.py
odoo/addons/product_pricelist_direct_print/wizards/__init__.py
odoo/addons/product_pricelist_direct_print/wizards/product_pricelist_print.py
odoo/addons/product_pricelist_direct_print/wizards/product_pricelist_print_view.xml
odoo_addon_product_pricelist_direct_print-18.0.1.0.1.3.dist-info/METADATA
odoo_addon_product_pricelist_direct_print-18.0.1.0.1.3.dist-info/WHEEL
odoo_addon_product_pricelist_direct_print-18.0.1.0.1.3.dist-info/top_level.txt
odoo_addon_product_pricelist_direct_print-18.0.1.0.1.3.dist-info/RECORD
