Metadata-Version: 2.1
Name: odoo-addon-product_pricelist_direct_print
Version: 18.0.1.0.1.3
Requires-Python: >=3.10
Requires-Dist: odoo==18.0.*
Summary: Print price list from menu option, product templates, products variants or price lists
Home-page: https://github.com/OCA/product-attribute
License: AGPL-3
Author: Tecnativa, GRAP, Odoo Community Association (OCA)
Author-email: support@odoo-community.org
Classifier: Programming Language :: Python
Classifier: Framework :: Odoo
Classifier: Framework :: Odoo :: 18.0
Classifier: License :: OSI Approved :: GNU Affero General Public License v3
